chanina/__init__.py
chanina/__main__.py
chanina/cli/__main__.py
chanina/cli/runner.py
chanina/core/__init__.py
chanina/core/bootstrapper.py
chanina/core/chanina.py
chanina/core/errors.py
chanina/core/features.py
chanina/core/worker_session.py
chanina/default_features.py
chanina/examples/__init__.py
chanina/examples/basic_usage.py
chanina/tools/__init__.py
chanina/tools/_meta_tools.py
chanina/tools/filters.py
chanina/tools/inspect.py
chanina/tools/interact.py
chanina/tools/navigate.py
chanina/tools/wait.py
chanina/utils.py
chanina-0.2.2.dist-info/METADATA
chanina-0.2.2.dist-info/WHEEL
chanina-0.2.2.dist-info/entry_points.txt
chanina-0.2.2.dist-info/RECORD
