Metadata-Version: 2.3
Name: chanina
Version: 0.2.2
Summary:  Chanina is a Python application to automate and orchestrate Playwright sessions using a Celery-based task system. 
Author: Leo Hehlen
Author-email: leo.hehlen@pc-rtx.com
Requires-Python: >=3.11
Classifier: Programming Language :: Python :: 3
Classifier: Programming Language :: Python :: 3.11
Classifier: Programming Language :: Python :: 3.12
Classifier: Programming Language :: Python :: 3.13
Requires-Dist: celery (>=5.5.3,<6.0.0)
Requires-Dist: colorama (>=0.4.6,<0.5.0)
Requires-Dist: playwright (>=1.52.0,<2.0.0)
Requires-Dist: pytest (>=8.3.5,<9.0.0)
Requires-Dist: pyyaml (>=6.0.2,<7.0.0)
Requires-Dist: redis (>=6.4.0,<7.0.0)
Requires-Dist: requests (>=2.32.3,<3.0.0)
Requires-Dist: uvicorn (>=0.38.0,<0.39.0)
Requires-Dist: werkzeug (>=3.1.3,<4.0.0)
